lumecode/__init__.py
lumecode/cli.py
lumecode/installer.py
lumecode_ai-1.0.0.dist-info/LICENSE
lumecode_ai-1.0.0.dist-info/METADATA
lumecode_ai-1.0.0.dist-info/WHEEL
lumecode_ai-1.0.0.dist-info/entry_points.txt
lumecode_ai-1.0.0.dist-info/top_level.txt
lumecode_ai-1.0.0.dist-info/RECORD
