Metadata-Version: 2.1
Name: lumecode-ai
Version: 1.0.0
Summary: AI-powered coding agent with multi-model LLM support
Home-page: https://github.com/anonymus-netizien/lumecode
Author: anonymus-netizien
Author-email: lumecode@example.com
Project-URL: Bug Tracker, https://github.com/anonymus-netizien/lumecode/issues
Project-URL: Documentation, https://github.com/anonymus-netizien/lumecode#readme
Project-URL: Source Code, https://github.com/anonymus-netizien/lumecode
Classifier: Development Status :: 5 - Production/Stable
Classifier: Environment :: Console
Classifier: Intended Audience :: Developers
Classifier: License :: OSI Approved :: MIT License
Classifier: Operating System :: OS Independent
Classifier: Programming Language :: Python :: 3
Classifier: Programming Language :: Python :: 3.8
Classifier: Programming Language :: Python :: 3.9
Classifier: Programming Language :: Python :: 3.10
Classifier: Programming Language :: Python :: 3.11
Classifier: Programming Language :: Python :: 3.12
Classifier: Topic :: Software Development
Classifier: Topic :: Software Development :: Code Generators
Requires-Python: >=3.8
License-File: LICENSE
Requires-Dist: requests>=2.28.0
Requires-Dist: platformdirs>=3.0.0
